hashlist/__init__.py
hashlist/hash_list.py
hashlist-0.0.8.dist-info/LICENSE
hashlist-0.0.8.dist-info/METADATA
hashlist-0.0.8.dist-info/WHEEL
hashlist-0.0.8.dist-info/top_level.txt
hashlist-0.0.8.dist-info/RECORD
