Metadata-Version: 2.1
Name: hashlist
Version: 0.0.8
Summary: Easy way to create and manage hash lists
Home-page: https://github.com/1Doomdie1/hashlist
Author: Doomdie
Author-email: doomdie.info@yahoo.com
License: UNKNOWN
Platform: UNKNOWN
Classifier: Programming Language :: Python :: 3
Classifier: License :: OSI Approved :: MIT License
Classifier: Operating System :: Unix
Classifier: Operating System :: MacOS :: MacOS X
Classifier: Operating System :: Microsoft :: Windows
Requires-Python: >=3.6
License-File: LICENSE
